setup.py
taskpool/__init__.py
taskpool/taskpool.py
taskpool/version.py
taskpool.egg-info/PKG-INFO
taskpool.egg-info/SOURCES.txt
taskpool.egg-info/dependency_links.txt
taskpool.egg-info/top_level.txt